customer_segmentation_clustering/__init__.py
customer_segmentation_clustering/cluster_scoring.py
customer_segmentation_clustering/data_preprocessing.py
customer_segmentation_clustering/feature_engineering.py
customer_segmentation_clustering/main.py
Custmr_segmentation-0.1.1.dist-info/LICENSE
Custmr_segmentation-0.1.1.dist-info/METADATA
Custmr_segmentation-0.1.1.dist-info/WHEEL
Custmr_segmentation-0.1.1.dist-info/top_level.txt
Custmr_segmentation-0.1.1.dist-info/RECORD
